webfocus/__init__.py
webfocus/bayes.py
webfocus/cleandata.py
webfocus/extractor.py
webfocus/label_func.py
webfocus/models.py
webfocus/run.py
webfocus/similarity.py
webfocus/statistics.py
webfocus/training.py
webfocus-0.13.dist-info/DESCRIPTION.rst
webfocus-0.13.dist-info/METADATA
webfocus-0.13.dist-info/RECORD
webfocus-0.13.dist-info/WHEEL
webfocus-0.13.dist-info/entry_points.txt
webfocus-0.13.dist-info/metadata.json
webfocus-0.13.dist-info/top_level.txt
