Metadata-Version: 2.0
Name: webfocus
Version: 0.13
Summary: extract the content from html docs
Home-page: https://github.com/qiulimao
Author: qiulimao
Author-email: qiu_limao@163.com
License: Apache License, Version 2.0
Keywords: html content extract
Platform: UNKNOWN
Classifier: Development Status :: 4 - Beta
Classifier: Programming Language :: Python :: 2
Classifier: Programming Language :: Python :: 2.6
Classifier: Programming Language :: Python :: 2.7
Classifier: Programming Language :: Python :: 3
Classifier: Programming Language :: Python :: 3.3
Classifier: Programming Language :: Python :: 3.4
Classifier: Programming Language :: Python :: 3.5
Classifier: License :: OSI Approved :: Apache Software License
Classifier: Intended Audience :: Developers
Classifier: Operating System :: OS Independent
Classifier: Topic :: Software Development :: Libraries :: Application Frameworks
Classifier: Topic :: Software Development :: Libraries :: Python Modules
Requires-Dist: chardet (>=2.2)
Requires-Dist: click (>=3.3)
Requires-Dist: cssselect (>=0.9)
Requires-Dist: lxml
Requires-Dist: pycurl
Requires-Dist: pyquery
Requires-Dist: pyquery
Requires-Dist: requests
Requires-Dist: requests (>=2.2)
Requires-Dist: six (>=1.5.0)
